pyroasts/__init__.py
pyroasts/__main__.py
pyroasts/helper.py
pyroasts/roasts.py
pyroasts-1.0.4.dist-info/LICENSE
pyroasts-1.0.4.dist-info/METADATA
pyroasts-1.0.4.dist-info/WHEEL
pyroasts-1.0.4.dist-info/entry_points.txt
pyroasts-1.0.4.dist-info/top_level.txt
pyroasts-1.0.4.dist-info/RECORD
