Metadata-Version: 2.1
Name: pyroasts
Version: 1.0.4
Summary: Python roast package. Developed with pyenv, built with build using setuptools, uploaded to PyPI using twine, and distributed via pip.
Author-email: Ian Pompliano <inp9194@nyu.edu>, Obinna Nwaokoro <ocn2006@nyu.edu>, Sanskriti Gupta <sg6479@nyu.edu>, Marko Todorovic <mat9407@nyu.edu>
License: GNU GENERAL PUBLIC LICENSE
Project-URL: Homepage, https://github.com/software-students-fall2024/3-python-package-all-stars-v3
Project-URL: Repository, https://github.com/software-students-fall2024/3-python-package-all-stars-v3.git
Project-URL: Bug Tracker, https://github.com/software-students-fall2024/3-python-package-all-stars-v3/issues
Keywords: python,package,build,tutorial
Classifier: Programming Language :: Python :: 3
Classifier: Intended Audience :: Education
Classifier: License :: OSI Approved :: GNU General Public License v3 (GPLv3)
Classifier: Operating System :: OS Independent
Requires-Python: >=3.7
License-File: LICENSE
Provides-Extra: dev
Requires-Dist: pytest; extra == "dev"
